{
  "friendly": "王者荣耀",
  "limiters": [
    {"id": "sgame2:cpu4", "step": -1, "mode": "BOTTOM", "max": 2150400, "min": 710400, "margin": 605, "smoothness": 15},
    {"id": "sgame2:cpu7", "step": -1, "mode": "BOTTOM", "max": 2361600, "min": 844800, "margin": 605, "smoothness": 16},

    {"id": "sgame3:cpu4", "step": -1, "mode": "BOTTOM", "max": 1958400, "min": 1574400, "margin": 695, "smoothness": 15},
    {"id": "sgame3:cpu7", "step": -1, "mode": "BOTTOM", "max": 2457600, "min": 1747200, "margin": 695, "smoothness": 16},

    {"id": "sgame4:cpu4", "step": -1, "mode": "performance", "max": 2419200, "turning": 2246400, "min": 1670400, "margin": 695, "smoothness": 15},
    {"id": "sgame4:cpu7", "step": -0.9, "mode": "performance", "max": 2841600, "turning": 2649600, "min": 1862400, "margin": 695, "smoothness": 15},

    {"id": "sgame5:cpu4", "step": -1, "mode": "performance", "max": 2419200, "turning": 2246400, "min": 1766400, "margin": 1000, "smoothness": 15},
    {"id": "sgame5:cpu7", "step": -0.7, "mode": "performance", "max": 3200000, "turning": 2841600, "min": 1862400, "margin": 1000, "smoothness": 15}
  ],
  "modes": [{
    "mode": ["powersave"],
    "call": [
      ["@limiters", "g1:cpu4", "g1:cpu7"]
    ]
  }, {
    "mode": ["balance"],
    "call": [
      ["@limiters", "sgame2:cpu4", "sgame2:cpu7"]
    ],
    "sensors": [
      {
        "sensor": "fps",
        "interval": 10000,
        "props": ["$cpu_max_0", "$cpu_max_4", "$cpu_max_7"],
        "rules": [
          { "threshold": [-1, 100], "values": ["1804800", "2342400", "2649600"], "enter_once": [["@limiters", "sgame3:cpu4", "sgame3:cpu7"]] },
          { "threshold": [99,  75], "values": ["1804800", "2246400", "2553600"], "enter_once": [["@limiters", "sgame2:cpu4", "sgame2:cpu7"]] },
          { "threshold": [70,  -1], "values": ["1804800", "1958400", "2073600"], "enter_once": [["@limiters", "sgame2:cpu4", "sgame2:cpu7"]] }
        ]
      }
    ]
  }, {
    "mode": ["performance"],
    "call": [
      ["@values", "max_freq", "1804800", "2419200", "2841600"],
      ["@limiters", "sgame3:cpu4", "sgame3:cpu7"]
    ],
    "sensors": [
      {
        "sensor": "fps",
        "interval": 10000,
        "props": ["$cpu_max_0", "$cpu_max_4", "$cpu_max_7"],
        "rules": [
          { "threshold": [-1, 100], "values": ["1804800", "2419200", "2841600"], "enter_once": [["@limiters", "sgame4:cpu4", "sgame4:cpu7"]] },
          { "threshold": [99,  75], "values": ["1804800", "2342400", "2649600"], "enter_once": [["@limiters", "sgame3:cpu4", "sgame3:cpu7"]] },
          { "threshold": [70,  -1], "values": ["1804800", "2054400", "2169600"], "enter_once": [["@limiters", "sgame3:cpu4", "sgame3:cpu7"]] }
        ]
      }
    ]
  }, {
    "mode": ["fast"],
    "call": [
      ["@limiters", "sgame4:cpu4", "sgame4:cpu7"]
    ],
    "sensors": [
      {
        "sensor": "fps",
        "interval": 10000,
        "props": ["$cpu_max_0", "$cpu_max_4", "$cpu_max_7"],
        "rules": [
          { "threshold": [-1, 100], "values": ["1804800", "2419200", "3200000"], "enter_once": [
            ["@limiters", "sgame5:cpu4", "sgame5:cpu7"],
            ["@values", "target_loads", "65", "65", "65"]]
          },
          { "threshold": [99,  75], "values": ["1804800", "2419200", "2841600"], "enter_once": [
            ["@limiters", "sgame4:cpu4", "sgame4:cpu7"],
            ["@values", "target_loads", "70", "70", "70"]]
          },
          { "threshold": [70,  -1], "values": ["1804800", "2150400", "2457600"], "enter_once": [
            ["@limiters", "sgame4:cpu4", "sgame4:cpu7"],
            ["@values", "target_loads", "70", "75", "75"]]
          }
        ]
      }
    ]
  }]
}